{
  "Plans (updated with SQL)": [
    {
      "plan": [
        {
          "function": "text2SQL(problem=\"What procedures were performed on patient 13833101 since September 2104?\", context=\"The database schema includes tables for patients, procedures, and dates. The current time is set to 2105-12-31 23:59:00. Ensure to retrieve subject_id together with other columns.\")",
          "problem": "What procedures were performed on patient 13833101 since September 2104?",
          "context": "The database schema includes tables for patients, procedures, and dates. The current time is set to 2105-12-31 23:59:00. Ensure to retrieve subject_id together with other columns.\"",
          "outputs": {
            "data": {
              "status": "success",
              "data": [
                {
                  "subject_id": 13833101,
                  "hadm_id": 21665911,
                  "icd_code": "02hv33z",
                  "charttime": "2104-09-25 00:00:00"
                },
                {
                  "subject_id": 13833101,
                  "hadm_id": 21970617,
                  "icd_code": "5a1d60z",
                  "charttime": "2105-12-06 13:14:00"
                },
                {
                  "subject_id": 13833101,
                  "hadm_id": 21970617,
                  "icd_code": "0fd98zx",
                  "charttime": "2105-12-06 13:14:00"
                },
                {
                  "subject_id": 13833101,
                  "hadm_id": 21970617,
                  "icd_code": "0045",
                  "charttime": "2105-12-06 13:14:00"
                },
                {
                  "subject_id": 13833101,
                  "hadm_id": 25341406,
                  "icd_code": "8872",
                  "charttime": "2105-12-24 00:00:00"
                },
                {
                  "subject_id": 13833101,
                  "hadm_id": 25341406,
                  "icd_code": "4513",
                  "charttime": "2105-12-20 00:00:00"
                },
                {
                  "subject_id": 13833101,
                  "hadm_id": 26296066,
                  "icd_code": "8801",
                  "charttime": "2104-12-24 00:00:00"
                },
                {
                  "subject_id": 13833101,
                  "hadm_id": 26296066,
                  "icd_code": "02100z9",
                  "charttime": "2104-12-26 00:00:00"
                },
                {
                  "subject_id": 13833101,
                  "hadm_id": 27341504,
                  "icd_code": "3899",
                  "charttime": "2105-11-15 16:03:00"
                },
                {
                  "subject_id": 13833101,
                  "hadm_id": 27341504,
                  "icd_code": "8879",
                  "charttime": "2105-11-03 00:00:00"
                },
                {
                  "subject_id": 13833101,
                  "hadm_id": 27341504,
                  "icd_code": "3897",
                  "charttime": "2105-11-15 16:03:00"
                },
                {
                  "subject_id": 13833101,
                  "hadm_id": 27341504,
                  "icd_code": "5a1945z",
                  "charttime": "2105-11-15 16:03:00"
                },
                {
                  "subject_id": 13833101,
                  "hadm_id": 27341504,
                  "icd_code": "8604",
                  "charttime": "2105-11-15 16:03:00"
                },
                {
                  "subject_id": 13833101,
                  "hadm_id": 27341504,
                  "icd_code": "8938",
                  "charttime": "2105-11-01 00:00:00"
                },
                {
                  "subject_id": 13833101,
                  "hadm_id": 27341504,
                  "icd_code": "4523",
                  "charttime": "2105-11-03 00:00:00"
                },
                {
                  "subject_id": 13833101,
                  "hadm_id": 27341504,
                  "icd_code": "07dr3zx",
                  "charttime": "2105-11-15 16:03:00"
                },
                {
                  "subject_id": 13833101,
                  "hadm_id": 27341504,
                  "icd_code": "4514",
                  "charttime": "2105-11-06 00:00:00"
                },
                {
                  "subject_id": 13833101,
                  "hadm_id": 28085193,
                  "icd_code": "0dp6xuz",
                  "charttime": "2104-09-08 00:00:00"
                },
                {
                  "subject_id": 13833101,
                  "hadm_id": 28085193,
                  "icd_code": "7935",
                  "charttime": "2104-09-09 00:00:00"
                },
                {
                  "subject_id": 13833101,
                  "hadm_id": 28085193,
                  "icd_code": "3606",
                  "charttime": "2104-09-08 00:00:00"
                },
                {
                  "subject_id": 13833101,
                  "hadm_id": 28085193,
                  "icd_code": "3e0g76z",
                  "charttime": "2104-09-09 00:00:00"
                },
                {
                  "subject_id": 13833101,
                  "hadm_id": 28085193,
                  "icd_code": "0qpb04z",
                  "charttime": "2104-09-08 00:00:00"
                },
                {
                  "subject_id": 13833101,
                  "hadm_id": 28085193,
                  "icd_code": "0dtp4zz",
                  "charttime": "2104-09-08 00:00:00"
                },
                {
                  "subject_id": 13833101,
                  "hadm_id": 28085193,
                  "icd_code": "7962",
                  "charttime": "2104-09-08 00:00:00"
                },
                {
                  "subject_id": 13833101,
                  "hadm_id": 28085193,
                  "icd_code": "5a1d70z",
                  "charttime": "2104-09-08 00:00:00"
                },
                {
                  "subject_id": 13833101,
                  "hadm_id": 28085193,
                  "icd_code": "9671",
                  "charttime": "2104-09-08 00:00:00"
                }
              ]
            },
            "input": {
              "problem": "What procedures were performed on patient 13833101 since September 2104?",
              "context": "The database schema includes tables for patients, procedures, and dates. The current time is set to 2105-12-31 23:59:00. Ensure to retrieve subject_id together with other columns."
            },
            "output": {
              "reasoning": "To find the procedures performed on patient 13833101 since September 2104, we need to query the PROCEDURES_ICD table. We will filter the records by subject_id and charttime to ensure we only retrieve procedures performed after September 2104. The relevant columns to retrieve are subject_id, hadm_id, icd_code, and charttime.",
              "SQL": "SELECT subject_id, hadm_id, icd_code, charttime FROM PROCEDURES_ICD WHERE subject_id = 13833101 AND charttime >= '2104-09-01'"
            }
          },
          "id": 1
        },
        {
          "function": "text2SQL(problem=\"Retrieve the study IDs for chest x-rays of patient 13833101 since September 2104.\", context=\"The database schema includes tables for patients, studies, and dates. The current time is set to 2105-12-31 23:59:00. Ensure to retrieve subject_id together with other columns.\")",
          "problem": "Retrieve the study IDs for chest x-rays of patient 13833101 since September 2104.",
          "context": "The database schema includes tables for patients, studies, and dates. The current time is set to 2105-12-31 23:59:00. Ensure to retrieve subject_id together with other columns.\"",
          "outputs": {
            "data": {
              "status": "success",
              "data": [
                {
                  "subject_id": 13833101,
                  "study_id": 51898305
                },
                {
                  "subject_id": 13833101,
                  "study_id": 54719086
                },
                {
                  "subject_id": 13833101,
                  "study_id": 57878681
                },
                {
                  "subject_id": 13833101,
                  "study_id": 56089857
                },
                {
                  "subject_id": 13833101,
                  "study_id": 52824297
                },
                {
                  "subject_id": 13833101,
                  "study_id": 51892967
                },
                {
                  "subject_id": 13833101,
                  "study_id": 59658712
                },
                {
                  "subject_id": 13833101,
                  "study_id": 57482930
                },
                {
                  "subject_id": 13833101,
                  "study_id": 59810560
                },
                {
                  "subject_id": 13833101,
                  "study_id": 50941142
                },
                {
                  "subject_id": 13833101,
                  "study_id": 50778852
                },
                {
                  "subject_id": 13833101,
                  "study_id": 59353298
                }
              ]
            },
            "input": {
              "problem": "Retrieve the study IDs for chest x-rays of patient 13833101 since September 2104.",
              "context": "The database schema includes tables for patients, studies, and dates. The current time is set to 2105-12-31 23:59:00. Ensure to retrieve subject_id together with other columns."
            },
            "output": {
              "reasoning": "To retrieve the study IDs for chest x-rays of patient 13833101 since September 2104, we need to query the TB_CXR table. We will filter the records by subject_id and ensure the studydatetime is greater than or equal to '2104-09-01'. We will select the subject_id and study_id columns to provide the necessary information.",
              "SQL": "SELECT subject_id, study_id FROM TB_CXR WHERE subject_id = 13833101 AND studydatetime >= '2104-09-01'"
            }
          },
          "id": 2
        },
        {
          "function": "image_analysis(question=\"Did the chest x-ray reveal pneumonia in the right mid lung zone?\", context=$2)",
          "question": "Did the chest x-ray reveal pneumonia in the right mid lung zone?",
          "context": "$2",
          "outputs": {
            "output": [
              [
                "no"
              ],
              [
                "yes"
              ],
              [],
              [],
              [
                "no"
              ],
              [
                "no"
              ],
              [
                "yes"
              ],
              [
                "yes"
              ],
              [
                "yes"
              ],
              [
                "yes"
              ],
              [
                "yes"
              ],
              [
                "no"
              ]
            ],
            "input": {
              "question": "Did the chest x-ray reveal pneumonia in the right mid lung zone?",
              "context": "{'status': 'success', 'data': [{'subject_id': 13833101, 'study_id': 51898305}, {'subject_id': 13833101, 'study_id': 54719086}, {'subject_id': 13833101, 'study_id': 57878681}, {'subject_id': 13833101, 'study_id': 56089857}, {'subject_id': 13833101, 'study_id': 52824297}, {'subject_id': 13833101, 'study_id': 51892967}, {'subject_id': 13833101, 'study_id': 59658712}, {'subject_id': 13833101, 'study_id': 57482930}, {'subject_id': 13833101, 'study_id': 59810560}, {'subject_id': 13833101, 'study_id': 50941142}, {'subject_id': 13833101, 'study_id': 50778852}, {'subject_id': 13833101, 'study_id': 59353298}]}"
            }
          },
          "id": 3
        },
        {
          "function": "join()",
          "id": 4
        }
      ]
    }
  ],
  "prediction": [
    [
      {
        "content": "Thought: The results show that multiple procedures were performed on patient 13833101 since September 2104. Additionally, the chest x-ray analysis indicates that pneumonia in the right mid lung zone was detected in some instances. Therefore, I have sufficient information to answer the user's question."
      },
      {
        "content": "{'Summary': 'Procedures were performed and pneumonia was detected in the right mid lung zone in some chest x-rays.', 'details': 'Patient 13833101 underwent multiple procedures since September 2104. The chest x-ray analysis revealed pneumonia in the right mid lung zone in some instances.', 'source': 'The information was obtained from the database queries and image analysis results.', 'inference':'pneumonia', 'extra explanation':'The chest x-ray analysis showed both positive and negative results for pneumonia in the right mid lung zone.'}"
      }
    ]
  ],
  "question": "was any procedure performed on patient 13833101 since 09/2104, and did a chest x-ray reveal pneumonia in the right mid lung zone within the same period?",
  "id": 179
}